atentry/__init__.py
atentry-1.0.0.dist-info/LICENSE
atentry-1.0.0.dist-info/WHEEL
atentry-1.0.0.dist-info/METADATA
atentry-1.0.0.dist-info/RECORD
