Metadata-Version: 2.1
Name: atentry
Version: 1.0.0
Summary: Never see `if __name__ == "__main__"` again!
Home-page: https://github.com/Ewpratten/atentry
License: GPLv3
Author: Evan Pratten
Author-email: ewpratten@gmail.com
Requires-Python: >=3.7,<4.0
Classifier: License :: Other/Proprietary License
Classifier: Programming Language :: Python :: 3
Classifier: Programming Language :: Python :: 3.10
Classifier: Programming Language :: Python :: 3.7
Classifier: Programming Language :: Python :: 3.8
Classifier: Programming Language :: Python :: 3.9
Project-URL: Repository, https://github.com/Ewpratten/atentry
